pacetype/__init__.py
pacetype/pacetype.py
pacetype-0.3.0.dist-info/licenses/LICENSE
pacetype-0.3.0.dist-info/METADATA
pacetype-0.3.0.dist-info/WHEEL
pacetype-0.3.0.dist-info/top_level.txt
pacetype-0.3.0.dist-info/RECORD
