Metadata-Version: 2.4
Name: pacetype
Version: 0.3.0
Summary: Type text and emojis character-by-character using clipboard paste.
Author-email: Alex M <alexmalone489@gmail.com>
License-Expression: MIT
Project-URL: Homepage, https://github.com/AMAMazing/Pacetype
Project-URL: Bug Tracker, https://github.com/AMAMazing/Pacetype/issues
Project-URL: Repository, https://github.com/AMAMazing/Pacetype
Keywords: pacetype,typing,automation,gui,pyautogui,pyperclip,emoji,clipboard
Classifier: Programming Language :: Python :: 3
Classifier: Operating System :: OS Independent
Classifier: Intended Audience :: Developers
Classifier: Topic :: Software Development :: Libraries :: Python Modules
Classifier: Topic :: Utilities
Requires-Python: >=3.7
License-File: LICENSE
Requires-Dist: pyperclip>=1.8.2
Requires-Dist: PyAutoGUI>=0.9.53
Dynamic: license-file
